[{
    "title": "Afternoon Delight",
    "description": "cunt",
    "score_value": 10
},
{   "title":  "Amazon",
    "description": "cunt",
    "score_value": 10
},
{   "title":  "Ape",
    "description": "cunt",
    "score_value": 10
},
{   "title":  "Ascent to Desire",
    "description": "cunt",
    "score_value": 10
},
{   "title":  "Backwards Slide",
    "description": "cunt",
    "score_value": 10
},
{   "title":  "Balancing Act",
    "description": "cunt",
    "score_value": 10
},
{   "title":  "Bandoleer",
    "description": "cunt",
    "score_value": 10
},
{   "title":  "Basket",
    "description": "cunt",
    "score_value": 10
},
{   "title":  "Bridge",
    "description": "cunt",
    "score_value": 10
},
{   "title":  "Butterfly",
    "description": "cunt",
    "score_value": 10
},
{   "title":  "Candle",
    "description": "cunt",
    "score_value": 10
},
{   "title":  "Catherine Wheel",
    "description": "cunt",
    "score_value": 10
},
{   "title":  "Challenge",
    "description": "cunt",
    "score_value": 10
},
{   "title":  "Clasp",
    "description": "cunt",
    "score_value": 10
},
{   "title":  "Classic",
    "description": "cunt",
    "score_value": 10
},
{   "title":  "Clip",
    "description": "cunt",
    "score_value": 10
},
{   "title":  "Close-Up",
    "description": "cunt",
    "score_value": 10
},
{   "title":  "Column",
    "description": "cunt",
    "score_value": 10
},
{   "title":  "Crisscross",
    "description": "cunt",
    "score_value": 10
},
{   "title":  "Cross",
    "description": "cunt",
    "score_value": 10
},
{   "title":  "Crossed Keys",
    "description": "cunt",
    "score_value": 10
},
{   "title":  "Crouching Tiger",
    "description": "cunt",
    "score_value": 10
},
{   "title":  "Curled Angel",
    "description": "cunt",
    "score_value": 10
},
{   "title":  "Deckchair",
    "description": "cunt",
    "score_value": 10
},
{   "title":  "Doggy Style",
    "description": "cunt",
    "score_value": 10
},
{   "title":  "Dolphin",
    "description": "cunt",
    "score_value": 10
},
{   "title":  "Double Decker",
    "description": "cunt",
    "score_value": 10
},
{   "title":  "Eagle",
    "description": "cunt",
    "score_value": 10
},
{   "title":  "Fan",
    "description": "cunt",
    "score_value": 10
},
{   "title":  "Fantastic Rocking Horse",
    "description": "cunt",
    "score_value": 10
},
{   "title":  "Fold",
    "description": "cunt",
    "score_value": 10
},
{   "title":  "Frog",
    "description": "cunt",
    "score_value": 10
},
{   "title":  "G-Force",
    "description": "cunt",
    "score_value": 10
},
{   "title":  "Galley",
    "description": "cunt",
    "score_value": 10
},
{   "title":  "Glowing Juniper",
    "description": "cunt",
    "score_value": 10
},
{   "title":  "Glowing Triangle",
    "description": "cunt",
    "score_value": 10
},
{   "title":  "Grip",
    "description": "cunt",
    "score_value": 10
},
{   "title":  "Hero",
    "description": "cunt",
    "score_value": 10
},
{   "title":  "Hinge",
    "description": "cunt",
    "score_value": 10
},
{   "title":  "Hound",
    "description": "cunt",
    "score_value": 10
},
{   "title":  "Indrani",
    "description": "cunt",
    "score_value": 10
},
{   "title":  "Kneel",
    "description": "cunt",
    "score_value": 10
},
{   "title":  "Kneeling Wheelbarrow",
    "description": "cunt",
    "score_value": 10
},
{   "title":  "Landslide",
    "description": "cunt",
    "score_value": 10
},
{   "title":  "Lotus Blossom",
    "description": "cunt",
    "score_value": 10
},
{   "title":  "Lustful Leg",
    "description": "cunt",
    "score_value": 10
},
{   "title":  "Magic Mountain",
    "description": "cunt",
    "score_value": 10
},
{   "title":  "Mermaid",
    "description": "cunt",
    "score_value": 10
},
{   "title":  "Nirvana",
    "description": "cunt",
    "score_value": 10
},
{   "title":  "Padlock",
    "description": "cunt",
    "score_value": 10
},
{   "title":  "Peg",
    "description": "cunt",
    "score_value": 10
},
{   "title":  "Plough",
    "description": "cunt",
    "score_value": 10
},
{   "title":  "Prone Tiger",
    "description": "cunt",
    "score_value": 10
},
{   "title":  "Propeller",
    "description": "cunt",
    "score_value": 10
},
{   "title":  "Proposal",
    "description": "cunt",
    "score_value": 10
},
{   "title":  "Reclining Lotus",
    "description": "cunt",
    "score_value": 10
},
{   "title":  "Reverse Cowgirl",
    "description": "cunt",
    "score_value": 10
},
{   "title":  "Right Angle",
    "description": "cunt",
    "score_value": 10
},
{   "title":  "Rock\"n Roller",
    "description": "cunt",
    "score_value": 10
},
{   "title":  "Rowing Boat",
    "description": "cunt",
    "score_value": 10
},
{   "title":  "Seated Ball",
    "description": "cunt",
    "score_value": 10
},
{   "title":  "Seduction",
    "description": "cunt",
    "score_value": 10
},
{   "title":  "Shoulder Stand",
    "description": "cunt",
    "score_value": 10
},
{   "title":  "Side Saddle",
    "description": "cunt",
    "score_value": 10
},
{   "title":  "Sidekick",
    "description": "cunt",
    "score_value": 10
},
{   "title":  "Sideways Samba",
    "description": "cunt",
    "score_value": 10
},
{   "title":  "Slide",
    "description": "cunt",
    "score_value": 10
},
{   "title":  "Slip",
    "description": "cunt",
    "score_value": 10
},
{   "title":  "Snail",
    "description": "cunt",
    "score_value": 10
},
{   "title":  "Sphinx",
    "description": "cunt",
    "score_value": 10
},
{   "title":  "Splitting Bamboo",
    "description": "cunt",
    "score_value": 10
},
{   "title":  "Squat Balance",
    "description": "cunt",
    "score_value": 10
},
{   "title":  "Stair Master",
    "description": "cunt",
    "score_value": 10
},
{   "title":  "Standing Wheelbarrow",
    "description": "cunt",
    "score_value": 10
},
{   "title":  "Star",
    "description": "cunt",
    "score_value": 10
},
{   "title":  "Spider",
    "description": "cunt",
    "score_value": 10
},
{   "title":  "Super 8",
    "description": "cunt",
    "score_value": 10
},
{   "title":  "Supernova",
    "description": "cunt",
    "score_value": 10
},
{   "title":  "Suspended Congress",
    "description": "cunt",
    "score_value": 10
},
{   "title":  "Suspended Scissors",
    "description": "cunt",
    "score_value": 10
},
{   "title":  "Thigh Master",
    "description": "cunt",
    "score_value": 10
},
{   "title":  "Toad",
    "description": "cunt",
    "score_value": 10
},
{   "title":  "Tominagi",
    "description": "cunt",
    "score_value": 10
},
{   "title":  "Triumph Arch",
    "description": "cunt",
    "score_value": 10
},
{   "title":  "Visitor",
    "description": "cunt",
    "score_value": 10
},
{   "title":  "Whisper",
    "description": "cunt",
    "score_value": 10
},
{   "title":  "Widely Open",
    "description": "cunt",
    "score_value": 10
},
{   "title":  "X Rated",
    "description": "cunt",
    "score_value": 10
},
{   "title":  "The Y Curve",
    "description": "cunt",
    "score_value": 10
}]